[
{"value":"0","categoryID":"0","label":"'#System'"},
{"value":"1","categoryID":"1","label":"Character"},
{"value":"2","categoryID":"1","label":"Corporation"},
{"value":"3","categoryID":"2","label":"Region"},
{"value":"4","categoryID":"2","label":"Constellation"},
{"value":"5","categoryID":"2","label":"Solar System"},
{"value":"6","categoryID":"2","label":"Sun"},
{"value":"7","categoryID":"2","label":"Planet"},
{"value":"8","categoryID":"2","label":"Moon"},
{"value":"9","categoryID":"2","label":"Asteroid Belt"},
{"value":"10","categoryID":"2","label":"Stargate"},
{"value":"11","categoryID":"2","label":"Asteroid OLD"},
{"value":"12","categoryID":"2","label":"Cargo Container"},
{"value":"13","categoryID":"2","label":"Ring"},
{"value":"14","categoryID":"2","label":"Biomass"},
{"value":"15","categoryID":"3","label":"Station"},
{"value":"16","categoryID":"3","label":"Station Services"},
{"value":"17","categoryID":"4","label":"Money"},
{"value":"18","categoryID":"4","label":"Mineral"},
{"value":"19","categoryID":"1","label":"Faction"},
{"value":"20","categoryID":"4","label":"Drug"},
{"value":"23","categoryID":"5","label":"Clone"},
{"value":"24","categoryID":"5","label":"Voucher"},
{"value":"25","categoryID":"6","label":"Frigate"},
{"value":"26","categoryID":"6","label":"Cruiser"},
{"value":"27","categoryID":"6","label":"Battleship"},
{"value":"28","categoryID":"6","label":"Industrial"},
{"value":"29","categoryID":"6","label":"Capsule"},
{"value":"30","categoryID":"6","label":"Titan"},
{"value":"31","categoryID":"6","label":"Shuttle"},
{"value":"32","categoryID":"1","label":"Alliance"},
{"value":"38","categoryID":"7","label":"Shield Extender"},
{"value":"39","categoryID":"7","label":"Shield Recharger"},
{"value":"40","categoryID":"7","label":"Shield Booster"},
{"value":"41","categoryID":"7","label":"Remote Shield Booster"},
{"value":"43","categoryID":"7","label":"Capacitor Recharger"},
{"value":"46","categoryID":"7","label":"Propulsion Module"},
{"value":"47","categoryID":"7","label":"Cargo Scanner"},
{"value":"48","categoryID":"7","label":"Ship Scanner"},
{"value":"49","categoryID":"7","label":"Survey Scanner"},
{"value":"52","categoryID":"7","label":"Warp Scrambler"},
{"value":"53","categoryID":"7","label":"Energy Weapon"},
{"value":"54","categoryID":"7","label":"Mining Laser"},
{"value":"55","categoryID":"7","label":"Projectile Weapon"},
{"value":"56","categoryID":"7","label":"Missile Launcher"},
{"value":"57","categoryID":"7","label":"Shield Power Relay"},
{"value":"59","categoryID":"7","label":"Gyrostabilizer"},
{"value":"60","categoryID":"7","label":"Damage Control"},
{"value":"61","categoryID":"7","label":"Capacitor Battery"},
{"value":"62","categoryID":"7","label":"Armor Repair Unit"},
{"value":"63","categoryID":"7","label":"Hull Repair Unit"},
{"value":"65","categoryID":"7","label":"Stasis Web"},
{"value":"67","categoryID":"7","label":"Remote Capacitor Transmitter"},
{"value":"68","categoryID":"7","label":"Energy Nosferatu"},
{"value":"71","categoryID":"7","label":"Energy Neutralizer"},
{"value":"72","categoryID":"7","label":"Smart Bomb"},
{"value":"74","categoryID":"7","label":"Hybrid Weapon"},
{"value":"76","categoryID":"7","label":"Capacitor Booster"},
{"value":"77","categoryID":"7","label":"Shield Hardener"},
{"value":"78","categoryID":"7","label":"Reinforced Bulkhead"},
{"value":"80","categoryID":"7","label":"Burst Jammer"},
{"value":"82","categoryID":"7","label":"Passive Targeting System"},
{"value":"83","categoryID":"8","label":"Projectile Ammo"},
{"value":"85","categoryID":"8","label":"Hybrid Charge"},
{"value":"86","categoryID":"8","label":"Frequency Crystal"},
{"value":"87","categoryID":"8","label":"Capacitor Booster Charge"},
{"value":"88","categoryID":"8","label":"Light Defender Missile"},
{"value":"89","categoryID":"8","label":"Torpedo"},
{"value":"90","categoryID":"8","label":"Bomb"},
{"value":"92","categoryID":"8","label":"Mine"},
{"value":"94","categoryID":"10","label":"Trading"},
{"value":"95","categoryID":"10","label":"Trade Session"},
{"value":"96","categoryID":"7","label":"Automated Targeting System"},
{"value":"97","categoryID":"18","label":"Proximity Drone"},
{"value":"98","categoryID":"7","label":"Armor Coating"},
{"value":"99","categoryID":"11","label":"Sentry Gun"},
{"value":"100","categoryID":"18","label":"Combat Drone"},
{"value":"101","categoryID":"18","label":"Mining Drone"},
{"value":"104","categoryID":"9","label":"Clone Blueprint"},
{"value":"105","categoryID":"9","label":"Frigate Blueprint"},
{"value":"106","categoryID":"9","label":"Cruiser Blueprint"},
{"value":"107","categoryID":"9","label":"Battleship Blueprint"},
{"value":"108","categoryID":"9","label":"Industrial Blueprint"},
{"value":"109","categoryID":"9","label":"Capsule Blueprint"},
{"value":"110","categoryID":"9","label":"Titan Blueprint"},
{"value":"111","categoryID":"9","label":"Shuttle Blueprint"},
{"value":"118","categoryID":"9","label":"Shield Extender Blueprint"},
{"value":"119","categoryID":"9","label":"Shield Recharger Blueprint"},
{"value":"120","categoryID":"9","label":"Shield Booster Blueprint"},
{"value":"121","categoryID":"9","label":"Remote Shield Booster Blueprint"},
{"value":"123","categoryID":"9","label":"Capacitor Recharger Blueprint"},
{"value":"126","categoryID":"9","label":"Propulsion Module Blueprint"},
{"value":"127","categoryID":"9","label":"Cargo Scanner Blueprint"},
{"value":"128","categoryID":"9","label":"Ship Scanner Blueprint"},
{"value":"129","categoryID":"9","label":"Survey Scanner Blueprint"},
{"value":"130","categoryID":"9","label":"ECM Blueprint"},
{"value":"131","categoryID":"9","label":"ECCM Blueprint"},
{"value":"132","categoryID":"9","label":"Warp Scrambler Blueprint"},
{"value":"133","categoryID":"9","label":"Energy Weapon Blueprint"},
{"value":"134","categoryID":"9","label":"Mining Laser Blueprint"},
{"value":"135","categoryID":"9","label":"Projectile Weapon Blueprint"},
{"value":"136","categoryID":"9","label":"Missile Launcher Blueprint"},
{"value":"137","categoryID":"9","label":"Power Manager Blueprint"},
{"value":"139","categoryID":"9","label":"Gunnery Upgrade Blueprint"},
{"value":"140","categoryID":"9","label":"Damage Control Blueprint"},
{"value":"141","categoryID":"9","label":"Capacitor Battery Blueprint"},
{"value":"142","categoryID":"9","label":"Armor Repair Unit Blueprint"},
{"value":"143","categoryID":"9","label":"Hull Repair Unit Blueprint"},
{"value":"145","categoryID":"9","label":"Stasis Web Blueprint"},
{"value":"147","categoryID":"9","label":"Remote Capacitor Transmitter Blueprint"},
{"value":"148","categoryID":"9","label":"Energy Nosferatu Blueprint"},
{"value":"151","categoryID":"9","label":"Energy Neutralizer Blueprint"},
{"value":"152","categoryID":"9","label":"Smart Bomb Blueprint"},
{"value":"154","categoryID":"9","label":"Hybrid Weapon Blueprint"},
{"value":"156","categoryID":"9","label":"Capacitor Booster Blueprint"},
{"value":"157","categoryID":"9","label":"Shield Hardener Blueprint"},
{"value":"158","categoryID":"9","label":"Hull Mods Blueprint"},
{"value":"160","categoryID":"9","label":"Burst Jammer Blueprint"},
{"value":"161","categoryID":"9","label":"Passive Targeting System Blueprint"},
{"value":"162","categoryID":"9","label":"Automated Targeting System Blueprint"},
{"value":"163","categoryID":"9","label":"Armor Coating Blueprint"},
{"value":"165","categoryID":"9","label":"Projectile Ammo Blueprint"},
{"value":"166","categoryID":"9","label":"Missile Blueprint"},
{"value":"167","categoryID":"9","label":"Hybrid Charge Blueprint"},
{"value":"168","categoryID":"9","label":"Frequency Crystal Blueprint"},
{"value":"169","categoryID":"9","label":"Capacitor Booster Charge Blueprint"},
{"value":"170","categoryID":"9","label":"Defender Missile Blueprint"},
{"value":"172","categoryID":"9","label":"Bomb Blueprint"},
{"value":"174","categoryID":"9","label":"Mine Blueprint"},
{"value":"175","categoryID":"9","label":"Proximity Drone Blueprint"},
{"value":"176","categoryID":"9","label":"Combat Drone Blueprint"},
{"value":"177","categoryID":"9","label":"Mining Drone Blueprint"},
{"value":"178","categoryID":"9","label":"Drug Blueprint"},
{"value":"180","categoryID":"11","label":"Protective Sentry Gun"},
{"value":"182","categoryID":"11","label":"Police Drone"},
{"value":"185","categoryID":"11","label":"Pirate Drone"},
{"value":"186","categoryID":"2","label":"Wreck"},
{"value":"190","categoryID":"14","label":"Bloodline Bonus"},
{"value":"191","categoryID":"14","label":"Physical Benefit"},
{"value":"192","categoryID":"14","label":"Physical Handicap"},
{"value":"193","categoryID":"14","label":"Phobia Handicap"},
{"value":"194","categoryID":"14","label":"Social Handicap"},
{"value":"195","categoryID":"14","label":"Amarr Education"},
{"value":"196","categoryID":"14","label":"Caldari Education"},
{"value":"197","categoryID":"14","label":"Gallente Education"},
{"value":"198","categoryID":"14","label":"Minmatar Education"},
{"value":"199","categoryID":"14","label":"Career Bonus"},
{"value":"201","categoryID":"7","label":"ECM"},
{"value":"202","categoryID":"7","label":"ECCM"},
{"value":"203","categoryID":"7","label":"Sensor Backup Array"},
{"value":"205","categoryID":"7","label":"Heat Sink"},
{"value":"208","categoryID":"7","label":"Sensor Dampener"},
{"value":"209","categoryID":"7","label":"Remote Tracking Computer"},
{"value":"210","categoryID":"7","label":"Signal Amplifier"},
{"value":"211","categoryID":"7","label":"Tracking Enhancer"},
{"value":"212","categoryID":"7","label":"Sensor Booster"},
{"value":"213","categoryID":"7","label":"Tracking Computer"},
{"value":"218","categoryID":"9","label":"Heat Sink Blueprint"},
{"value":"223","categoryID":"9","label":"Sensor Booster Blueprint"},
{"value":"224","categoryID":"9","label":"Tracking Computer Blueprint"},
{"value":"225","categoryID":"7","label":"Cheat Module Group"},
{"value":"226","categoryID":"2","label":"Large Collidable Object"},
{"value":"227","categoryID":"2","label":"Cloud"},
{"value":"237","categoryID":"6","label":"Rookie ship"},
{"value":"255","categoryID":"16","label":"Gunnery"},
{"value":"256","categoryID":"16","label":"Missiles"},
{"value":"257","categoryID":"16","label":"Spaceship Command"},
{"value":"258","categoryID":"16","label":"Leadership"},
{"value":"266","categoryID":"16","label":"Corporation Management"},
{"value":"267","categoryID":"17","label":"Obsolete Books"},
{"value":"268","categoryID":"16","label":"Production"},
{"value":"269","categoryID":"16","label":"Rigging"},
{"value":"270","categoryID":"16","label":"Science"},
{"value":"272","categoryID":"16","label":"Electronic Systems"},
{"value":"273","categoryID":"16","label":"Drones"},
{"value":"274","categoryID":"16","label":"Trade"},
{"value":"275","categoryID":"16","label":"Navigation"},
{"value":"278","categoryID":"16","label":"Social"},
{"value":"279","categoryID":"11","label":"LCO Drone"},
{"value":"280","categoryID":"17","label":"General"},
{"value":"281","categoryID":"17","label":"Frozen"},
{"value":"282","categoryID":"17","label":"Radioactive"},
{"value":"283","categoryID":"17","label":"Livestock"},
{"value":"284","categoryID":"17","label":"Biohazard"},
{"value":"285","categoryID":"7","label":"CPU Enhancer"},
{"value":"286","categoryID":"11","label":"Minor Threat"},
{"value":"287","categoryID":"11","label":"Rogue Drone"},
{"value":"288","categoryID":"11","label":"Faction Drone"},
{"value":"289","categoryID":"7","label":"Projected ECCM"},
{"value":"290","categoryID":"7","label":"Remote Sensor Booster"},
{"value":"291","categoryID":"7","label":"Weapon Disruptor"},
{"value":"295","categoryID":"7","label":"Shield Amplifier"},
{"value":"296","categoryID":"9","label":"Shield Amplifier Blueprint"},
{"value":"297","categoryID":"11","label":"Convoy"},
{"value":"298","categoryID":"11","label":"Convoy Drone"},
{"value":"299","categoryID":"18","label":"Repair Drone"},
{"value":"300","categoryID":"20","label":"Cyberimplant"},
{"value":"301","categoryID":"11","label":"Concord Drone"},
{"value":"302","categoryID":"7","label":"Magnetic Field Stabilizer"},
{"value":"303","categoryID":"20","label":"Booster"},
{"value":"304","categoryID":"20","label":"DNA Mutator"},
{"value":"305","categoryID":"2","label":"Comet"},
{"value":"306","categoryID":"11","label":"Spawn Container"},
{"value":"307","categoryID":"2","label":"Construction Platform"},
{"value":"308","categoryID":"7","label":"Countermeasure Launcher"},
{"value":"309","categoryID":"7","label":"Autopilot"},
{"value":"310","categoryID":"2","label":"Beacon"},
{"value":"311","categoryID":"23","label":"Reprocessing Array"},
{"value":"312","categoryID":"2","label":"Planetary Cloud"},
{"value":"313","categoryID":"17","label":"Drugs"},
{"value":"314","categoryID":"17","label":"Miscellaneous"},
{"value":"315","categoryID":"7","label":"Warp Core Stabilizer"},
{"value":"316","categoryID":"7","label":"Gang Coordinator"},
{"value":"317","categoryID":"7","label":"Computer Interface Node"},
{"value":"318","categoryID":"2","label":"Landmark"},
{"value":"319","categoryID":"11","label":"Large Collidable Structure"},
{"value":"321","categoryID":"7","label":"Shield Disruptor"},
{"value":"323","categoryID":"11","label":"Billboard"},
{"value":"324","categoryID":"6","label":"Assault Frigate"},
{"value":"325","categoryID":"7","label":"Remote Armor Repairer"},
{"value":"326","categoryID":"7","label":"Armor Plating Energized"},
{"value":"328","categoryID":"7","label":"Armor Hardener"},
{"value":"329","categoryID":"7","label":"Armor Reinforcer"},
{"value":"330","categoryID":"7","label":"Cloaking Device"},
{"value":"332","categoryID":"17","label":"Tool"},
{"value":"333","categoryID":"17","label":"Datacores"},
{"value":"334","categoryID":"17","label":"Construction Components"},
{"value":"335","categoryID":"11","label":"Temporary Cloud"},
{"value":"336","categoryID":"2","label":"Mobile Sentry Gun"},
{"value":"337","categoryID":"11","label":"Mission Drone"},
{"value":"338","categoryID":"7","label":"Shield Boost Amplifier"},
{"value":"339","categoryID":"7","label":"Auxiliary Power Core"},
{"value":"340","categoryID":"2","label":"Secure Cargo Container"},
{"value":"341","categoryID":"7","label":"Signature Scrambling"},
{"value":"342","categoryID":"9","label":"Anti Warp Scrambler Blueprint"},
{"value":"343","categoryID":"9","label":"Weapon Disruptor Blueprint"},
{"value":"344","categoryID":"9","label":"Tracking Enhancer Blueprint"},
{"value":"345","categoryID":"9","label":"Remote Tracking Computer Blueprint"},
{"value":"346","categoryID":"9","label":"Co-Processor Blueprint"},
{"value":"347","categoryID":"9","label":"Signal Amplifier Blueprint"},
{"value":"348","categoryID":"9","label":"Armor Hardener Blueprint"},
{"value":"349","categoryID":"9","label":"Armor Reinforcer Blueprint"},
{"value":"350","categoryID":"9","label":"Remote Armor Repairer Blueprint"},
{"value":"352","categoryID":"9","label":"Auxiliary Power Core Blueprint"},
{"value":"353","categoryID":"7","label":"QA Module"},
{"value":"355","categoryID":"17","label":"Refinables"},
{"value":"356","categoryID":"9","label":"Tool Blueprint"},
{"value":"357","categoryID":"7","label":"DroneBayExpander"},
{"value":"358","categoryID":"6","label":"Heavy Assault Cruiser"},
{"value":"360","categoryID":"9","label":"Shield Boost Amplifier Blueprint"},
{"value":"361","categoryID":"22","label":"Mobile Warp Disruptor"},
{"value":"363","categoryID":"23","label":"Ship Maintenance Array"},
{"value":"364","categoryID":"23","label":"Mobile Storage"},
{"value":"365","categoryID":"23","label":"Control Tower"},
{"value":"366","categoryID":"2","label":"Warp Gate"},
{"value":"367","categoryID":"7","label":"Ballistic Control system"},
{"value":"368","categoryID":"2","label":"Global Warp Disruptor"},
{"value":"369","categoryID":"17","label":"Ship Logs"},
{"value":"370","categoryID":"17","label":"Criminal Tags"},
{"value":"371","categoryID":"9","label":"Mobile Warp Disruptor Blueprint"},
{"value":"372","categoryID":"8","label":"Advanced Autocannon Ammo"},
{"value":"373","categoryID":"8","label":"Advanced Railgun Charge"},
{"value":"374","categoryID":"8","label":"Advanced Beam Laser Crystal"},
{"value":"375","categoryID":"8","label":"Advanced Pulse Laser Crystal"},
{"value":"376","categoryID":"8","label":"Advanced Artillery Ammo"},
{"value":"377","categoryID":"8","label":"Advanced Blaster Charge"},
{"value":"378","categoryID":"7","label":"Cruise Control"},
{"value":"379","categoryID":"7","label":"Target Painter"},
{"value":"380","categoryID":"6","label":"Deep Space Transport"},
{"value":"381","categoryID":"6","label":"Elite Battleship"},
{"value":"382","categoryID":"2","label":"Shipping Crates"},
{"value":"383","categoryID":"11","label":"Destructible Sentry Gun"},
{"value":"384","categoryID":"8","label":"Light Missile"},
{"value":"385","categoryID":"8","label":"Heavy Missile"},
{"value":"386","categoryID":"8","label":"Cruise Missile"},
{"value":"387","categoryID":"8","label":"Rocket"},
{"value":"394","categoryID":"8","label":"FoF Light Missile"},
{"value":"395","categoryID":"8","label":"FoF Heavy Missile"},
{"value":"396","categoryID":"8","label":"FoF Cruise Missile"},
{"value":"397","categoryID":"23","label":"Assembly Array"},
{"value":"400","categoryID":"9","label":"Ballistic Control System Blueprint"},
{"value":"401","categoryID":"9","label":"Cloaking Device Blueprint"},
{"value":"404","categoryID":"23","label":"Silo"},
{"value":"405","categoryID":"7","label":"Anti Cloaking Pulse"},
{"value":"406","categoryID":"7","label":"Smartbomb Supercharger"},
{"value":"407","categoryID":"7","label":"Drone Control Unit"},
{"value":"408","categoryID":"9","label":"Drone Upgrade Blueprint"},
{"value":"409","categoryID":"17","label":"Empire Insignia Drops"},
{"value":"410","categoryID":"9","label":"Anti Cloaking Pulse Blueprint"},
{"value":"411","categoryID":"2","label":"Force Field"},
{"value":"413","categoryID":"23","label":"Laboratory"},
{"value":"414","categoryID":"23","label":"Mobile Power Core"},
{"value":"416","categoryID":"23","label":"Moon Mining"},
{"value":"417","categoryID":"23","label":"Mobile Missile Sentry"},
{"value":"418","categoryID":"23","label":"Mobile Shield Generator"},
{"value":"419","categoryID":"6","label":"Combat Battlecruiser"},
{"value":"420","categoryID":"6","label":"Destroyer"},
{"value":"422","categoryID":"4","label":"Gas Isotopes"},
{"value":"423","categoryID":"4","label":"Ice Product"},
{"value":"425","categoryID":"8","label":"Orbital Assault Unit"},
{"value":"426","categoryID":"23","label":"Mobile Projectile Sentry"},
{"value":"427","categoryID":"4","label":"Moon Materials"},
{"value":"428","categoryID":"4","label":"Intermediate Materials"},
{"value":"429","categoryID":"4","label":"Composite"},
{"value":"430","categoryID":"23","label":"Mobile Laser Sentry"},
{"value":"435","categoryID":"11","label":"Deadspace Overseer"},
{"value":"436","categoryID":"24","label":"Simple Reaction"},
{"value":"438","categoryID":"23","label":"Mobile Reactor"},
{"value":"439","categoryID":"23","label":"Electronic Warfare Battery"},
{"value":"440","categoryID":"23","label":"Sensor Dampening Battery"},
{"value":"441","categoryID":"23","label":"Stasis Webification Battery"},
{"value":"443","categoryID":"23","label":"Warp Scrambling Battery"},
{"value":"444","categoryID":"23","label":"Shield Hardening Array"},
{"value":"445","categoryID":"23","label":"Force Field Array"},
{"value":"446","categoryID":"11","label":"Customs Official"},
{"value":"447","categoryID":"9","label":"Construction Component Blueprints"},
{"value":"448","categoryID":"2","label":"Audit Log Secure Container"},
{"value":"449","categoryID":"23","label":"Mobile Hybrid Sentry"},
{"value":"450","categoryID":"25","label":"Arkonor"},
{"value":"451","categoryID":"25","label":"Bistot"},
{"value":"452","categoryID":"25","label":"Crokite"},
{"value":"453","categoryID":"25","label":"Dark Ochre"},
{"value":"454","categoryID":"25","label":"Hedbergite"},
{"value":"455","categoryID":"25","label":"Hemorphite"},
{"value":"456","categoryID":"25","label":"Jaspet"},
{"value":"457","categoryID":"25","label":"Kernite"},
{"value":"458","categoryID":"25","label":"Plagioclase"},
{"value":"459","categoryID":"25","label":"Pyroxeres"},
{"value":"460","categoryID":"25","label":"Scordite"},
{"value":"461","categoryID":"25","label":"Spodumain"},
{"value":"462","categoryID":"25","label":"Veldspar"},
{"value":"463","categoryID":"6","label":"Mining Barge"},
{"value":"464","categoryID":"7","label":"Strip Miner"},
{"value":"465","categoryID":"25","label":"Ice"},
{"value":"467","categoryID":"25","label":"Gneiss"},
{"value":"468","categoryID":"25","label":"Mercoxit"},
{"value":"469","categoryID":"25","label":"Omber"},
{"value":"470","categoryID":"18","label":"Unanchoring Drone"},
{"value":"471","categoryID":"23","label":"Corporate Hangar Array"},
{"value":"472","categoryID":"7","label":"System Scanner"},
{"value":"473","categoryID":"23","label":"Tracking Array"},
{"value":"474","categoryID":"17","label":"Acceleration Gate Keys"},
{"value":"475","categoryID":"7","label":"Microwarpdrive"},
{"value":"476","categoryID":"8","label":"Capital Torpedo"},
{"value":"477","categoryID":"9","label":"Mining Barge Blueprint"},
{"value":"478","categoryID":"9","label":"System Scanner Blueprint"},
{"value":"479","categoryID":"8","label":"Scanner Probe"},
{"value":"480","categoryID":"23","label":"Stealth Emitter Array"},
{"value":"481","categoryID":"7","label":"Scan Probe Launcher"},
{"value":"482","categoryID":"8","label":"Mining Crystal"},
{"value":"483","categoryID":"7","label":"Frequency Mining Laser"},
{"value":"484","categoryID":"24","label":"Complex Reactions"},
{"value":"485","categoryID":"6","label":"Dreadnought"},
{"value":"486","categoryID":"9","label":"Scan Probe Blueprint"},
{"value":"487","categoryID":"9","label":"Destroyer Blueprint"},
{"value":"489","categoryID":"9","label":"Battlecruiser Blueprint"},
{"value":"490","categoryID":"9","label":"Strip Miner Blueprint"},
{"value":"492","categoryID":"8","label":"Survey Probe"},
{"value":"493","categoryID":"17","label":"Overseer Personal Effects"},
{"value":"494","categoryID":"11","label":"Deadspace Overseer's Structure"},
{"value":"495","categoryID":"11","label":"Deadspace Overseer's Sentry"},
{"value":"496","categoryID":"11","label":"Deadspace Overseer's Belongings"},
{"value":"497","categoryID":"8","label":"Fuel"},
{"value":"498","categoryID":"8","label":"Modifications"},
{"value":"499","categoryID":"7","label":"New EW Testing"},
{"value":"500","categoryID":"8","label":"Festival Charges"},
{"value":"501","categoryID":"7","label":"Festival Launcher"},
{"value":"502","categoryID":"2","label":"Cosmic Signature"},
{"value":"503","categoryID":"9","label":"Elite Industrial Blueprint"},
{"value":"504","categoryID":"9","label":"Target Painter Blueprint"},
{"value":"505","categoryID":"16","label":"Fake Skills"},
{"value":"506","categoryID":"7","label":"Missile Launcher Cruise"},
{"value":"507","categoryID":"7","label":"Missile Launcher Rocket"},
{"value":"508","categoryID":"7","label":"Missile Launcher Torpedo"},
{"value":"509","categoryID":"7","label":"Missile Launcher Light"},
{"value":"510","categoryID":"7","label":"Missile Launcher Heavy"},
{"value":"511","categoryID":"7","label":"Missile Launcher Rapid Light"},
{"value":"512","categoryID":"7","label":"Missile Launcher Defender"},
{"value":"513","categoryID":"6","label":"Freighter"},
{"value":"514","categoryID":"7","label":"ECM Stabilizer"},
{"value":"515","categoryID":"7","label":"Siege Module"},
{"value":"516","categoryID":"9","label":"Siege Module Blueprint"},
{"value":"517","categoryID":"2","label":"Agents in Space"},
{"value":"518","categoryID":"7","label":"Anti Ballistic Defense System"},
{"value":"519","categoryID":"25","label":"Terran Artifacts"},
{"value":"520","categoryID":"11","label":"Storyline Frigate"},
{"value":"521","categoryID":"17","label":"Identification"},
{"value":"522","categoryID":"11","label":"Storyline Cruiser"},
{"value":"523","categoryID":"11","label":"Storyline Battleship"},
{"value":"524","categoryID":"7","label":"'XL Missile Launcher '"},
{"value":"525","categoryID":"9","label":"Freighter Blueprint"},
{"value":"526","categoryID":"17","label":"Commodities"},
{"value":"527","categoryID":"11","label":"Storyline Mission Frigate"},
{"value":"528","categoryID":"17","label":"Artifacts and Prototypes"},
{"value":"530","categoryID":"17","label":"Materials and Compounds"},
{"value":"532","categoryID":"9","label":"Gang Coordinator Blueprint"},
{"value":"533","categoryID":"11","label":"Storyline Mission Cruiser"},
{"value":"534","categoryID":"11","label":"Storyline Mission Battleship"},
{"value":"535","categoryID":"9","label":"Construction Platform Blueprint"},
{"value":"536","categoryID":"17","label":"Station Components"},
{"value":"537","categoryID":"9","label":"Dreadnought Blueprint"},
{"value":"538","categoryID":"7","label":"Data Miners"},
{"value":"540","categoryID":"6","label":"Command Ship"},
{"value":"541","categoryID":"6","label":"Interdictor"},
{"value":"543","categoryID":"6","label":"Exhumer"},
{"value":"544","categoryID":"18","label":"Energy Neutralizer Drone"},
{"value":"545","categoryID":"18","label":"Warp Scrambling Drone"},
{"value":"546","categoryID":"7","label":"Mining Upgrade"},
{"value":"547","categoryID":"6","label":"Carrier"},
{"value":"548","categoryID":"8","label":"Interdiction Probe"},
{"value":"549","categoryID":"18","label":"Fighter Drone"},
{"value":"550","categoryID":"11","label":"Asteroid Angel Cartel Frigate"},
{"value":"551","categoryID":"11","label":"Asteroid Angel Cartel Cruiser"},
{"value":"552","categoryID":"11","label":"Asteroid Angel Cartel Battleship"},
{"value":"553","categoryID":"11","label":"Asteroid Angel Cartel Officer"},
{"value":"554","categoryID":"11","label":"Asteroid Angel Cartel Hauler"},
{"value":"555","categoryID":"11","label":"Asteroid Blood Raiders Cruiser"},
{"value":"556","categoryID":"11","label":"Asteroid Blood Raiders Battleship"},
{"value":"557","categoryID":"11","label":"Asteroid Blood Raiders Frigate"},
{"value":"558","categoryID":"11","label":"Asteroid Blood Raiders Hauler"},
{"value":"559","categoryID":"11","label":"Asteroid Blood Raiders Officer"},
{"value":"560","categoryID":"11","label":"Asteroid Guristas Battleship"},
{"value":"561","categoryID":"11","label":"Asteroid Guristas Cruiser"},
{"value":"562","categoryID":"11","label":"Asteroid Guristas Frigate"},
{"value":"563","categoryID":"11","label":"Asteroid Guristas Hauler"},
{"value":"564","categoryID":"11","label":"Asteroid Guristas Officer"},
{"value":"565","categoryID":"11","label":"Asteroid Sansha's Nation Battleship"},
{"value":"566","categoryID":"11","label":"Asteroid Sansha's Nation Cruiser"},
{"value":"567","categoryID":"11","label":"Asteroid Sansha's Nation Frigate"},
{"value":"568","categoryID":"11","label":"Asteroid Sansha's Nation Hauler"},
{"value":"569","categoryID":"11","label":"Asteroid Sansha's Nation Officer"},
{"value":"570","categoryID":"11","label":"Asteroid Serpentis Battleship"},
{"value":"571","categoryID":"11","label":"Asteroid Serpentis Cruiser"},
{"value":"572","categoryID":"11","label":"Asteroid Serpentis Frigate"},
{"value":"573","categoryID":"11","label":"Asteroid Serpentis Hauler"},
{"value":"574","categoryID":"11","label":"Asteroid Serpentis Officer"},
{"value":"575","categoryID":"11","label":"Asteroid Angel Cartel Destroyer"},
{"value":"576","categoryID":"11","label":"Asteroid Angel Cartel BattleCruiser"},
{"value":"577","categoryID":"11","label":"Asteroid Blood Raiders Destroyer"},
{"value":"578","categoryID":"11","label":"Asteroid Blood Raiders BattleCruiser"},
{"value":"579","categoryID":"11","label":"Asteroid Guristas Destroyer"},
{"value":"580","categoryID":"11","label":"Asteroid Guristas BattleCruiser"},
{"value":"581","categoryID":"11","label":"Asteroid Sansha's Nation Destroyer"},
{"value":"582","categoryID":"11","label":"Asteroid Sansha's Nation BattleCruiser"},
{"value":"583","categoryID":"11","label":"Asteroid Serpentis Destroyer"},
{"value":"584","categoryID":"11","label":"Asteroid Serpentis BattleCruiser"},
{"value":"585","categoryID":"7","label":"Remote Hull Repairer"},
{"value":"586","categoryID":"7","label":"Drone Modules"},
{"value":"588","categoryID":"7","label":"Super Weapon"},
{"value":"589","categoryID":"7","label":"Interdiction Sphere Launcher"},
{"value":"590","categoryID":"7","label":"Jump Portal Generator"},
{"value":"593","categoryID":"11","label":"Deadspace Angel Cartel BattleCruiser"},
{"value":"594","categoryID":"11","label":"Deadspace Angel Cartel Battleship"},
{"value":"595","categoryID":"11","label":"Deadspace Angel Cartel Cruiser"},
{"value":"596","categoryID":"11","label":"Deadspace Angel Cartel Destroyer"},
{"value":"597","categoryID":"11","label":"Deadspace Angel Cartel Frigate"},
{"value":"602","categoryID":"11","label":"Deadspace Blood Raiders BattleCruiser"},
{"value":"603","categoryID":"11","label":"Deadspace Blood Raiders Battleship"},
{"value":"604","categoryID":"11","label":"Deadspace Blood Raiders Cruiser"},
{"value":"605","categoryID":"11","label":"Deadspace Blood Raiders Destroyer"},
{"value":"606","categoryID":"11","label":"Deadspace Blood Raiders Frigate"},
{"value":"611","categoryID":"11","label":"Deadspace Guristas BattleCruiser"},
{"value":"612","categoryID":"11","label":"Deadspace Guristas Battleship"},
{"value":"613","categoryID":"11","label":"Deadspace Guristas Cruiser"},
{"value":"614","categoryID":"11","label":"Deadspace Guristas Destroyer"},
{"value":"615","categoryID":"11","label":"Deadspace Guristas Frigate"},
{"value":"620","categoryID":"11","label":"Deadspace Sansha's Nation BattleCruiser"},
{"value":"621","categoryID":"11","label":"Deadspace Sansha's Nation Battleship"},
{"value":"622","categoryID":"11","label":"Deadspace Sansha's Nation Cruiser"},
{"value":"623","categoryID":"11","label":"Deadspace Sansha's Nation Destroyer"},
{"value":"624","categoryID":"11","label":"Deadspace Sansha's Nation Frigate"},
{"value":"629","categoryID":"11","label":"Deadspace Serpentis BattleCruiser"},
{"value":"630","categoryID":"11","label":"Deadspace Serpentis Battleship"},
{"value":"631","categoryID":"11","label":"Deadspace Serpentis Cruiser"},
{"value":"632","categoryID":"11","label":"Deadspace Serpentis Destroyer"},
{"value":"633","categoryID":"11","label":"Deadspace Serpentis Frigate"},
{"value":"638","categoryID":"7","label":"Navigation Computer"},
{"value":"639","categoryID":"18","label":"Electronic Warfare Drone"},
{"value":"640","categoryID":"18","label":"Logistic Drone"},
{"value":"641","categoryID":"18","label":"Stasis Webifying Drone"},
{"value":"642","categoryID":"7","label":"Super Gang Enhancer"},
{"value":"643","categoryID":"9","label":"Carrier Blueprint"},
{"value":"644","categoryID":"7","label":"Drone Navigation Computer"},
{"value":"645","categoryID":"7","label":"Drone Damage Modules"},
{"value":"646","categoryID":"7","label":"Drone Tracking Modules"},
{"value":"647","categoryID":"7","label":"Drone Control Range Module"},
{"value":"648","categoryID":"8","label":"Advanced Rocket"},
{"value":"649","categoryID":"2","label":"Freight Container"},
{"value":"650","categoryID":"7","label":"Tractor Beam"},
{"value":"651","categoryID":"9","label":"Super Weapon Blueprint"},
{"value":"652","categoryID":"17","label":"Lease"},
{"value":"653","categoryID":"8","label":"Advanced Light Missile"},
{"value":"654","categoryID":"8","label":"Advanced Heavy Assault Missile"},
{"value":"655","categoryID":"8","label":"Advanced Heavy Missile"},
{"value":"656","categoryID":"8","label":"Advanced Cruise Missile"},
{"value":"657","categoryID":"8","label":"Advanced Torpedo"},
{"value":"658","categoryID":"7","label":"Cynosural Field"},
{"value":"659","categoryID":"6","label":"Supercarrier"},
{"value":"660","categoryID":"7","label":"Energy Vampire Slayer"},
{"value":"661","categoryID":"24","label":"Simple Biochemical Reactions"},
{"value":"662","categoryID":"24","label":"Complex Biochemical Reactions"},
{"value":"663","categoryID":"8","label":"Mercoxit Mining Crystal"},
{"value":"665","categoryID":"11","label":"Mission Amarr Empire Frigate"},
{"value":"666","categoryID":"11","label":"Mission Amarr Empire Battlecruiser"},
{"value":"667","categoryID":"11","label":"Mission Amarr Empire Battleship"},
{"value":"668","categoryID":"11","label":"Mission Amarr Empire Cruiser"},
{"value":"669","categoryID":"11","label":"Mission Amarr Empire Destroyer"},
{"value":"670","categoryID":"11","label":"Mission Amarr Empire Other"},
{"value":"671","categoryID":"11","label":"Mission Caldari State Frigate"},
{"value":"672","categoryID":"11","label":"Mission Caldari State Battlecruiser"},
{"value":"673","categoryID":"11","label":"Mission Caldari State Cruiser"},
{"value":"674","categoryID":"11","label":"Mission Caldari State Battleship"},
{"value":"675","categoryID":"11","label":"Mission Caldari State Other"},
{"value":"676","categoryID":"11","label":"Mission Caldari State Destroyer"},
{"value":"677","categoryID":"11","label":"Mission Gallente Federation Frigate"},
{"value":"678","categoryID":"11","label":"Mission Gallente Federation Cruiser"},
{"value":"679","categoryID":"11","label":"Mission Gallente Federation Destroyer"},
{"value":"680","categoryID":"11","label":"Mission Gallente Federation Battleship"},
{"value":"681","categoryID":"11","label":"Mission Gallente Federation Battlecruiser"},
{"value":"682","categoryID":"11","label":"Mission Gallente Federation Other"},
{"value":"683","categoryID":"11","label":"Mission Minmatar Republic Frigate"},
{"value":"684","categoryID":"11","label":"Mission Minmatar Republic Destroyer"},
{"value":"685","categoryID":"11","label":"Mission Minmatar Republic Battlecruiser"},
{"value":"686","categoryID":"11","label":"Mission Minmatar Republic Other"},
{"value":"687","categoryID":"11","label":"Mission Khanid Frigate"},
{"value":"688","categoryID":"11","label":"Mission Khanid Destroyer"},
{"value":"689","categoryID":"11","label":"Mission Khanid Cruiser"},
{"value":"690","categoryID":"11","label":"Mission Khanid Battlecruiser"},
{"value":"691","categoryID":"11","label":"Mission Khanid Battleship"},
{"value":"692","categoryID":"11","label":"Mission Khanid Other"},
{"value":"693","categoryID":"11","label":"Mission CONCORD Frigate"},
{"value":"694","categoryID":"11","label":"Mission CONCORD Destroyer"},
{"value":"695","categoryID":"11","label":"Mission CONCORD Cruiser"},
{"value":"696","categoryID":"11","label":"Mission CONCORD Battlecruiser"},
{"value":"697","categoryID":"11","label":"Mission CONCORD Battleship"},
{"value":"698","categoryID":"11","label":"Mission CONCORD Other"},
{"value":"699","categoryID":"11","label":"Mission Mordu Frigate"},
{"value":"700","categoryID":"11","label":"Mission Mordu Destroyer"},
{"value":"701","categoryID":"11","label":"Mission Mordu Cruiser"},
{"value":"702","categoryID":"11","label":"Mission Mordu Battlecruiser"},
{"value":"703","categoryID":"11","label":"Mission Mordu Battleship"},
{"value":"704","categoryID":"11","label":"Mission Mordu Other"},
{"value":"705","categoryID":"11","label":"Mission Minmatar Republic Cruiser"},
{"value":"706","categoryID":"11","label":"Mission Minmatar Republic Battleship"},
{"value":"707","categoryID":"23","label":"Jump Portal Array"},
{"value":"709","categoryID":"23","label":"Scanner Array"},
{"value":"710","categoryID":"23","label":"Logistics Array"},
{"value":"711","categoryID":"2","label":"Harvestable Cloud"},
{"value":"712","categoryID":"4","label":"Biochemical Material"},
{"value":"715","categoryID":"11","label":"Destructible Agents In Space"},
{"value":"716","categoryID":"17","label":"Data Interfaces"},
{"value":"718","categoryID":"9","label":"Booster Blueprints"},
{"value":"721","categoryID":"20","label":"Temp"},
{"value":"722","categoryID":"9","label":"Advanced Hybrid Charge Blueprint"},
{"value":"723","categoryID":"9","label":"Tractor Beam Blueprint"},
{"value":"724","categoryID":"9","label":"Implant Blueprints"},
{"value":"725","categoryID":"9","label":"Advanced Projectile Ammo Blueprint"},
{"value":"726","categoryID":"9","label":"Advanced Frequency Crystal Blueprint"},
{"value":"727","categoryID":"9","label":"Mining Crystal Blueprint"},
{"value":"728","categoryID":"35","label":"Decryptors - Amarr"},
{"value":"729","categoryID":"35","label":"Decryptors - Minmatar"},
{"value":"730","categoryID":"35","label":"Decryptors - Gallente"},
{"value":"731","categoryID":"35","label":"Decryptors - Caldari"},
{"value":"732","categoryID":"17","label":"Decryptors - Sleepers"},
{"value":"733","categoryID":"17","label":"Decryptors - Yan Jung"},
{"value":"734","categoryID":"17","label":"Decryptors - Takmahl"},
{"value":"735","categoryID":"17","label":"Decryptors - Talocan"},
{"value":"737","categoryID":"7","label":"Gas Cloud Harvester"},
{"value":"738","categoryID":"20","label":"Cyber Armor"},
{"value":"739","categoryID":"20","label":"Cyber Drones"},
{"value":"740","categoryID":"20","label":"Cyber Electronic Systems"},
{"value":"741","categoryID":"20","label":"Cyber Engineering"},
{"value":"742","categoryID":"20","label":"Cyber Gunnery"},
{"value":"743","categoryID":"20","label":"Cyber Production"},
{"value":"744","categoryID":"20","label":"Cyber Leadership"},
{"value":"745","categoryID":"20","label":"Cyber Learning"},
{"value":"746","categoryID":"20","label":"Cyber Missile"},
{"value":"747","categoryID":"20","label":"Cyber Navigation"},
{"value":"748","categoryID":"20","label":"Cyber Science"},
{"value":"749","categoryID":"20","label":"Cyber Shields"},
{"value":"750","categoryID":"20","label":"Cyber Social"},
{"value":"751","categoryID":"20","label":"Cyber Trade"},
{"value":"753","categoryID":"7","label":"ECM Enhancer"},
{"value":"754","categoryID":"4","label":"Salvaged Materials"},
{"value":"755","categoryID":"11","label":"Asteroid Rogue Drone BattleCruiser"},
{"value":"756","categoryID":"11","label":"Asteroid Rogue Drone Battleship"},
{"value":"757","categoryID":"11","label":"Asteroid Rogue Drone Cruiser"},
{"value":"758","categoryID":"11","label":"Asteroid Rogue Drone Destroyer"},
{"value":"759","categoryID":"11","label":"Asteroid Rogue Drone Frigate"},
{"value":"760","categoryID":"11","label":"Asteroid Rogue Drone Hauler"},
{"value":"761","categoryID":"11","label":"Asteroid Rogue Drone Swarm"},
{"value":"762","categoryID":"7","label":"Inertial Stabilizer"},
{"value":"763","categoryID":"7","label":"Nanofiber Internal Structure"},
{"value":"764","categoryID":"7","label":"Overdrive Injector System"},
{"value":"765","categoryID":"7","label":"Expanded Cargohold"},
{"value":"766","categoryID":"7","label":"Power Diagnostic System"},
{"value":"767","categoryID":"7","label":"Capacitor Power Relay"},
{"value":"768","categoryID":"7","label":"Capacitor Flux Coil"},
{"value":"769","categoryID":"7","label":"Reactor Control Unit"},
{"value":"770","categoryID":"7","label":"Shield Flux Coil"},
{"value":"771","categoryID":"7","label":"Missile Launcher Heavy Assault"},
{"value":"772","categoryID":"8","label":"Heavy Assault Missile"},
{"value":"773","categoryID":"7","label":"Rig Armor"},
{"value":"774","categoryID":"7","label":"Rig Shield"},
{"value":"775","categoryID":"7","label":"Rig Energy Weapon"},
{"value":"776","categoryID":"7","label":"Rig Hybrid Weapon"},
{"value":"777","categoryID":"7","label":"Rig Projectile Weapon"},
{"value":"778","categoryID":"7","label":"Rig Drones"},
{"value":"779","categoryID":"7","label":"Rig Launcher"},
{"value":"781","categoryID":"7","label":"Rig Core"},
{"value":"782","categoryID":"7","label":"Rig Navigation"},
{"value":"783","categoryID":"20","label":"Cyber X Specials"},
{"value":"784","categoryID":"11","label":"Large Collidable Ship"},
{"value":"786","categoryID":"7","label":"Rig Electronic Systems"},
{"value":"787","categoryID":"9","label":"Rig Blueprint"},
{"value":"789","categoryID":"11","label":"Asteroid Angel Cartel Commander Frigate"},
{"value":"790","categoryID":"11","label":"Asteroid Angel Cartel Commander Cruiser"},
{"value":"791","categoryID":"11","label":"Asteroid Blood Raiders Commander Cruiser"},
{"value":"792","categoryID":"11","label":"Asteroid Blood Raiders Commander Frigate"},
{"value":"793","categoryID":"11","label":"Asteroid Angel Cartel Commander BattleCruiser"},
{"value":"794","categoryID":"11","label":"Asteroid Angel Cartel Commander Destroyer"},
{"value":"795","categoryID":"11","label":"Asteroid Blood Raiders Commander BattleCruiser"},
{"value":"796","categoryID":"11","label":"Asteroid Blood Raiders Commander Destroyer"},
{"value":"797","categoryID":"11","label":"Asteroid Guristas Commander BattleCruiser"},
{"value":"798","categoryID":"11","label":"Asteroid Guristas Commander Cruiser"},
{"value":"799","categoryID":"11","label":"Asteroid Guristas Commander Destroyer"},
{"value":"800","categoryID":"11","label":"Asteroid Guristas Commander Frigate"},
{"value":"801","categoryID":"11","label":"Deadspace Rogue Drone BattleCruiser"},
{"value":"802","categoryID":"11","label":"Deadspace Rogue Drone Battleship"},
{"value":"803","categoryID":"11","label":"Deadspace Rogue Drone Cruiser"},
{"value":"804","categoryID":"11","label":"Deadspace Rogue Drone Destroyer"},
{"value":"805","categoryID":"11","label":"Deadspace Rogue Drone Frigate"},
{"value":"806","categoryID":"11","label":"Deadspace Rogue Drone Swarm"},
{"value":"807","categoryID":"11","label":"Asteroid Sansha's Nation Commander BattleCruiser"},
{"value":"808","categoryID":"11","label":"Asteroid Sansha's Nation Commander Cruiser"},
{"value":"809","categoryID":"11","label":"Asteroid Sansha's Nation Commander Destroyer"},
{"value":"810","categoryID":"11","label":"Asteroid Sansha's Nation Commander Frigate"},
{"value":"811","categoryID":"11","label":"Asteroid Serpentis Commander BattleCruiser"},
{"value":"812","categoryID":"11","label":"Asteroid Serpentis Commander Cruiser"},
{"value":"813","categoryID":"11","label":"Asteroid Serpentis Commander Destroyer"},
{"value":"814","categoryID":"11","label":"Asteroid Serpentis Commander Frigate"},
{"value":"815","categoryID":"7","label":"Clone Vat Bay"},
{"value":"816","categoryID":"11","label":"Mission Generic Battleships"},
{"value":"817","categoryID":"11","label":"Mission Generic Cruisers"},
{"value":"818","categoryID":"11","label":"Mission Generic Frigates"},
{"value":"819","categoryID":"11","label":"Deadspace Overseer Frigate"},
{"value":"820","categoryID":"11","label":"Deadspace Overseer Cruiser"},
{"value":"821","categoryID":"11","label":"Deadspace Overseer Battleship"},
{"value":"822","categoryID":"11","label":"Mission Thukker Battlecruiser"},
{"value":"823","categoryID":"11","label":"Mission Thukker Battleship"},
{"value":"824","categoryID":"11","label":"Mission Thukker Cruiser"},
{"value":"825","categoryID":"11","label":"Mission Thukker Destroyer"},
{"value":"826","categoryID":"11","label":"Mission Thukker Frigate"},
{"value":"827","categoryID":"11","label":"Mission Thukker Other"},
{"value":"828","categoryID":"11","label":"Mission Generic Battle Cruisers"},
{"value":"829","categoryID":"11","label":"Mission Generic Destroyers"},
{"value":"830","categoryID":"6","label":"Covert Ops"},
{"value":"831","categoryID":"6","label":"Interceptor"},
{"value":"832","categoryID":"6","label":"Logistics"},
{"value":"833","categoryID":"6","label":"Force Recon Ship"},
{"value":"834","categoryID":"6","label":"Stealth Bomber"},
{"value":"835","categoryID":"2","label":"Station Upgrade Platform"},
{"value":"836","categoryID":"2","label":"Station Improvement Platform"},
{"value":"837","categoryID":"23","label":"Energy Neutralizing Battery"},
{"value":"838","categoryID":"23","label":"Cynosural Generator Array"},
{"value":"839","categoryID":"23","label":"Cynosural System Jammer"},
{"value":"840","categoryID":"23","label":"Structure Repair Array"},
{"value":"841","categoryID":"9","label":"Starbase - Control Tower Blueprints"},
{"value":"842","categoryID":"7","label":"Remote ECM Burst"},
{"value":"843","categoryID":"11","label":"Asteroid Rogue Drone Commander BattleCruiser"},
{"value":"844","categoryID":"11","label":"Asteroid Rogue Drone Commander Battleship"},
{"value":"845","categoryID":"11","label":"Asteroid Rogue Drone Commander Cruiser"},
{"value":"846","categoryID":"11","label":"Asteroid Rogue Drone Commander Destroyer"},
{"value":"847","categoryID":"11","label":"Asteroid Rogue Drone Commander Frigate"},
{"value":"848","categoryID":"11","label":"Asteroid Angel Cartel Commander Battleship"},
{"value":"849","categoryID":"11","label":"Asteroid Blood Raiders Commander Battleship"},
{"value":"850","categoryID":"11","label":"Asteroid Guristas Commander Battleship"},
{"value":"851","categoryID":"11","label":"Asteroid Sansha's Nation Commander Battleship"},
{"value":"852","categoryID":"11","label":"Asteroid Serpentis Commander Battleship"},
{"value":"853","categoryID":"9","label":"Starbase - Laser Battery Blueprints"},
{"value":"854","categoryID":"9","label":"Starbase - Projectile Battery Blueprints"},
{"value":"855","categoryID":"9","label":"Starbase - Hybrid Battery Blueprints"},
{"value":"856","categoryID":"9","label":"Starbase - ECM Jamming Array Blueprints"},
{"value":"857","categoryID":"9","label":"Starbase - Warp Scrambling Battery Blueprints"},
{"value":"858","categoryID":"9","label":"Starbase - Stasis Webification Battery Blueprints"},
{"value":"859","categoryID":"9","label":"Starbase - Sensor Dampening Array Blueprints"},
{"value":"860","categoryID":"9","label":"Starbase - Energy Neutralizing Battery Blueprints"},
{"value":"861","categoryID":"11","label":"Mission Fighter Drone"},
{"value":"862","categoryID":"7","label":"Missile Launcher Bomb"},
{"value":"863","categoryID":"8","label":"Bomb ECM"},
{"value":"864","categoryID":"8","label":"Bomb Energy"},
{"value":"865","categoryID":"11","label":"Mission Amarr Empire Carrier"},
{"value":"866","categoryID":"11","label":"Mission Caldari State Carrier"},
{"value":"867","categoryID":"11","label":"Mission Gallente Federation Carrier"},
{"value":"868","categoryID":"11","label":"Mission Minmatar Republic Carrier"},
{"value":"870","categoryID":"9","label":"Remote Hull Repairer Blueprint"},
{"value":"871","categoryID":"9","label":"Starbase - Missile Battery Blueprints"},
{"value":"872","categoryID":"5","label":"Outpost Improvements"},
{"value":"873","categoryID":"17","label":"Capital Construction Components"},
{"value":"874","categoryID":"2","label":"Disruptable Station Services"},
{"value":"875","categoryID":"11","label":"Mission Faction Transports"},
{"value":"876","categoryID":"5","label":"Outpost Upgrades"},
{"value":"877","categoryID":"23","label":"Target Painting Battery"},
{"value":"878","categoryID":"7","label":"Cloak Enhancements"},
{"value":"879","categoryID":"17","label":"Slave Reception"},
{"value":"880","categoryID":"17","label":"Sleeper Components"},
{"value":"881","categoryID":"24","label":"Freedom Programs"},
{"value":"882","categoryID":"24","label":"Enslavement Programs"},
{"value":"883","categoryID":"6","label":"Capital Industrial Ship"},
{"value":"884","categoryID":"17","label":"Test Compressed Ore"},
{"value":"885","categoryID":"2","label":"Cosmic Anomaly"},
{"value":"886","categoryID":"4","label":"Rogue Drone Components"},
{"value":"888","categoryID":"9","label":"Ore Compression Blueprints"},
{"value":"889","categoryID":"9","label":"Ore Enhancement Blueprints"},
{"value":"890","categoryID":"9","label":"Ice Compression Blueprints"},
{"value":"891","categoryID":"9","label":"Starbase - Mobile Laboratory Blueprints"},
{"value":"892","categoryID":"8","label":"Planet Satellites"},
{"value":"893","categoryID":"6","label":"Electronic Attack Ship"},
{"value":"894","categoryID":"6","label":"Heavy Interdiction Cruiser"},
{"value":"896","categoryID":"7","label":"Rig Security Transponder"},
{"value":"897","categoryID":"2","label":"Covert Beacon"},
{"value":"898","categoryID":"6","label":"Black Ops"},
{"value":"899","categoryID":"7","label":"Warp Disrupt Field Generator"},
{"value":"900","categoryID":"6","label":"Marauder"},
{"value":"901","categoryID":"7","label":"Mining Enhancer"},
{"value":"902","categoryID":"6","label":"Jump Freighter"},
{"value":"903","categoryID":"25","label":"Ancient Compressed Ice"},
{"value":"904","categoryID":"7","label":"Rig Mining"},
{"value":"905","categoryID":"7","label":"Covert Cynosural Field Generator"},
{"value":"906","categoryID":"6","label":"Combat Recon Ship"},
{"value":"907","categoryID":"8","label":"Tracking Script"},
{"value":"908","categoryID":"8","label":"Warp Disruption Script"},
{"value":"909","categoryID":"8","label":"Tracking Disruption Script"},
{"value":"910","categoryID":"8","label":"Sensor Booster Script"},
{"value":"911","categoryID":"8","label":"Sensor Dampener Script"},
{"value":"912","categoryID":"9","label":"Script Blueprint"},
{"value":"913","categoryID":"17","label":"Advanced Capital Construction Components"},
{"value":"914","categoryID":"9","label":"Advanced Capital Construction Component Blueprints"},
{"value":"915","categoryID":"9","label":"Capital Construction Blueprints"},
{"value":"916","categoryID":"8","label":"Nanite Repair Paste"},
{"value":"917","categoryID":"9","label":"Data Miner Blueprint"},
{"value":"918","categoryID":"9","label":"Scan Probe Launcher Blueprint"},
{"value":"920","categoryID":"2","label":"Effect Beacon"},
{"value":"922","categoryID":"11","label":"Capture Point"},
{"value":"924","categoryID":"11","label":"Mission Faction Battleship"},
{"value":"925","categoryID":"11","label":"FW Infrastructure Hub"},
{"value":"927","categoryID":"11","label":"Mission Faction Industrials"},
{"value":"934","categoryID":"11","label":"Zombie Entities"},
{"value":"935","categoryID":"26","label":"WorldSpace"},
{"value":"937","categoryID":"29","label":"Decorations"},
{"value":"940","categoryID":"49","label":"Furniture"},
{"value":"941","categoryID":"6","label":"Industrial Command Ship"},
{"value":"943","categoryID":"5","label":"Game Time"},
{"value":"944","categoryID":"9","label":"Capital Industrial Ship Blueprint"},
{"value":"945","categoryID":"9","label":"Industrial Command Ship Blueprint"},
{"value":"952","categoryID":"11","label":"Mission Container"},
{"value":"954","categoryID":"32","label":"Defensive Systems"},
{"value":"955","categoryID":"32","label":"Electronic Systems"},
{"value":"956","categoryID":"32","label":"Offensive Systems"},
{"value":"957","categoryID":"32","label":"Propulsion Systems"},
{"value":"958","categoryID":"32","label":"Engineering Systems"},
{"value":"959","categoryID":"11","label":"Deadspace Sleeper Sleepless Sentinel"},
{"value":"960","categoryID":"11","label":"Deadspace Sleeper Awakened Sentinel"},
{"value":"961","categoryID":"11","label":"Deadspace Sleeper Emergent Sentinel"},
{"value":"963","categoryID":"6","label":"Strategic Cruiser"},
{"value":"964","categoryID":"17","label":"Hybrid Tech Components"},
{"value":"965","categoryID":"9","label":"Hybrid Component Blueprints"},
{"value":"966","categoryID":"4","label":"Ancient Salvage"},
{"value":"967","categoryID":"4","label":"Wormhole Minerals"},
{"value":"971","categoryID":"34","label":"Sleeper Propulsion Relics"},
{"value":"972","categoryID":"8","label":"Obsolete Probes"},
{"value":"973","categoryID":"9","label":"Subsystem Blueprints"},
{"value":"974","categoryID":"4","label":"Hybrid Polymers"},
{"value":"976","categoryID":"63","label":"Festival Charges Expired"},
{"value":"977","categoryID":"24","label":"Hybrid Reactions"},
{"value":"979","categoryID":"35","label":"Decryptors - Hybrid"},
{"value":"982","categoryID":"11","label":"Deadspace Sleeper Sleepless Defender"},
{"value":"983","categoryID":"11","label":"Deadspace Sleeper Sleepless Patroller"},
{"value":"984","categoryID":"11","label":"Deadspace Sleeper Awakened Defender"},
{"value":"985","categoryID":"11","label":"Deadspace Sleeper Awakened Patroller"},
{"value":"986","categoryID":"11","label":"Deadspace Sleeper Emergent Defender"},
{"value":"987","categoryID":"11","label":"Deadspace Sleeper Emergent Patroller"},
{"value":"988","categoryID":"2","label":"Wormhole"},
{"value":"990","categoryID":"34","label":"Sleeper Electronics Relics"},
{"value":"991","categoryID":"34","label":"Sleeper Offensive Relics"},
{"value":"992","categoryID":"34","label":"Sleeper Engineering Relics"},
{"value":"993","categoryID":"34","label":"Sleeper Defensive Relics"},
{"value":"995","categoryID":"2","label":"Secondary Sun"},
{"value":"996","categoryID":"9","label":"Strategic Cruiser Blueprints"},
{"value":"997","categoryID":"34","label":"Sleeper Hull Relics"},
{"value":"1003","categoryID":"40","label":"Territorial Claim Unit"},
{"value":"1004","categoryID":"40","label":"Defense Bunkers"},
{"value":"1005","categoryID":"40","label":"Sovereignty Blockade Unit"},
{"value":"1006","categoryID":"11","label":"Mission Faction Cruiser"},
{"value":"1007","categoryID":"11","label":"Mission Faction Frigate"},
{"value":"1010","categoryID":"8","label":"Compact XL Torpedo"},
{"value":"1012","categoryID":"40","label":"Infrastructure Hub"},
{"value":"1013","categoryID":"9","label":"Supercarrier Blueprints"},
{"value":"1016","categoryID":"39","label":"Strategic Upgrades"},
{"value":"1019","categoryID":"8","label":"Capital Cruise"},
{"value":"1020","categoryID":"39","label":"Industrial Upgrades"},
{"value":"1021","categoryID":"39","label":"Military Upgrades"},
{"value":"1022","categoryID":"6","label":"Prototype Exploration Ship"},
{"value":"1023","categoryID":"18","label":"Fighter Bomber"},
{"value":"1025","categoryID":"46","label":"Orbital Infrastructure"},
{"value":"1026","categoryID":"41","label":"Extractors"},
{"value":"1027","categoryID":"41","label":"Command Centers"},
{"value":"1028","categoryID":"41","label":"Processors"},
{"value":"1029","categoryID":"41","label":"Storage Facilities"},
{"value":"1030","categoryID":"41","label":"Spaceports"},
{"value":"1031","categoryID":"17","label":"Planetary Resources"},
{"value":"1032","categoryID":"42","label":"Planet Solid"},
{"value":"1033","categoryID":"42","label":"Planet Liquid-Gas"},
{"value":"1034","categoryID":"43","label":"Refined Commodities"},
{"value":"1035","categoryID":"42","label":"Planet Organic"},
{"value":"1036","categoryID":"41","label":"Planetary Links"},
{"value":"1040","categoryID":"43","label":"Specialized Commodities"},
{"value":"1041","categoryID":"43","label":"Advanced Commodities"},
{"value":"1042","categoryID":"43","label":"Basic Commodities"},
{"value":"1045","categoryID":"9","label":"Sovereignty Structure Blueprint"},
{"value":"1046","categoryID":"9","label":"Nanite Repair Paste Blueprint"},
{"value":"1048","categoryID":"9","label":"Starbase Blueprint"},
{"value":"1051","categoryID":"11","label":"Incursion Sansha's Nation Industrial"},
{"value":"1052","categoryID":"11","label":"Incursion Sansha's Nation Capital"},
{"value":"1053","categoryID":"11","label":"Incursion Sansha's Nation Frigate"},
{"value":"1054","categoryID":"11","label":"Incursion Sansha's Nation Cruiser"},
{"value":"1056","categoryID":"11","label":"Incursion Sansha's Nation Battleship"},
{"value":"1063","categoryID":"41","label":"Extractor Control Units"},
{"value":"1067","categoryID":"26","label":"MaterialZone"},
{"value":"1068","categoryID":"26","label":"DetailMesh"},
{"value":"1071","categoryID":"2","label":"Flashpoint"},
{"value":"1073","categoryID":"46","label":"Test Orbitals"},
{"value":"1079","categoryID":"49","label":"Generic"},
{"value":"1081","categoryID":"41","label":"Mercenary Bases"},
{"value":"1082","categoryID":"41","label":"Capsuleer Bases"},
{"value":"1083","categoryID":"30","label":"Eyewear"},
{"value":"1084","categoryID":"30","label":"Tattoos"},
{"value":"1085","categoryID":"30","label":"Piercings"},
{"value":"1086","categoryID":"30","label":"Scars"},
{"value":"1087","categoryID":"30","label":"Mid Layer"},
{"value":"1088","categoryID":"30","label":"Outer"},
{"value":"1089","categoryID":"30","label":"Tops"},
{"value":"1090","categoryID":"30","label":"Bottoms"},
{"value":"1091","categoryID":"30","label":"Footwear"},
{"value":"1092","categoryID":"30","label":"Hair Styles"},
{"value":"1093","categoryID":"30","label":"Makeup"},
{"value":"1105","categoryID":"53","label":"Lens Flares"},
{"value":"1106","categoryID":"46","label":"Orbital Construction Platform"},
{"value":"1107","categoryID":"53","label":"Particle Systems"},
{"value":"1108","categoryID":"53","label":"Animated Lights"},
{"value":"1109","categoryID":"29","label":"Audio"},
{"value":"1110","categoryID":"54","label":"Point Lights"},
{"value":"1111","categoryID":"54","label":"Box Lights"},
{"value":"1112","categoryID":"54","label":"Spot Lights"},
{"value":"1118","categoryID":"17","label":"Surface Infrastructure Prefab Units"},
{"value":"1121","categoryID":"29","label":"Perception Points"},
{"value":"1122","categoryID":"7","label":"Salvager"},
{"value":"1123","categoryID":"9","label":"Salvager Blueprint"},
{"value":"1126","categoryID":"59","label":"PhysicalPortals"},
{"value":"1136","categoryID":"4","label":"Fuel Block"},
{"value":"1137","categoryID":"9","label":"Fuel Block Blueprint"},
{"value":"1139","categoryID":"9","label":"Mining Laser Upgrade Blueprint"},
{"value":"1141","categoryID":"17","label":"Research Data"},
{"value":"1142","categoryID":"9","label":"Energy Neutralizer Drone Blueprint"},
{"value":"1143","categoryID":"9","label":"Electronic Warfare Drone Blueprint"},
{"value":"1144","categoryID":"9","label":"Logistic Drone Blueprint"},
{"value":"1145","categoryID":"9","label":"Fighter Bomber Blueprint"},
{"value":"1146","categoryID":"9","label":"Fighter Drone Blueprint"},
{"value":"1147","categoryID":"9","label":"Stasis Webifying Drone Blueprint"},
{"value":"1149","categoryID":"22","label":"Mobile Jump Disruptor"},
{"value":"1150","categoryID":"7","label":"Armor Resistance Shift Hardener"},
{"value":"1151","categoryID":"9","label":"Armor Resistance Shift Hardener Blueprint"},
{"value":"1152","categoryID":"9","label":"Drone Damage Module Blueprint"},
{"value":"1153","categoryID":"8","label":"Shield Booster Script"},
{"value":"1154","categoryID":"7","label":"Target Breaker"},
{"value":"1155","categoryID":"9","label":"Target Breaker Blueprint"},
{"value":"1156","categoryID":"7","label":"Fueled Shield Booster"},
{"value":"1157","categoryID":"9","label":"Fueled Shield Booster Blueprint"},
{"value":"1158","categoryID":"8","label":"Heavy Defender Missile"},
{"value":"1159","categoryID":"18","label":"Salvage Drone"},
{"value":"1160","categoryID":"9","label":"Survey Probe Blueprints"},
{"value":"1162","categoryID":"9","label":"Container Blueprints"},
{"value":"1165","categoryID":"2","label":"Satellite"},
{"value":"1166","categoryID":"11","label":"FW Minmatar Republic Frigate"},
{"value":"1167","categoryID":"11","label":"FW Caldari State Frigate"},
{"value":"1168","categoryID":"11","label":"FW Gallente Federation Frigate"},
{"value":"1169","categoryID":"11","label":"FW Amarr Empire Frigate"},
{"value":"1174","categoryID":"11","label":"Asteroid Rogue Drone Officer"},
{"value":"1175","categoryID":"11","label":"FW Amarr Empire Destroyer"},
{"value":"1176","categoryID":"11","label":"FW Caldari State Destroyer"},
{"value":"1177","categoryID":"11","label":"FW Gallente Federation Destroyer"},
{"value":"1178","categoryID":"11","label":"FW Minmatar Republic Destroyer"},
{"value":"1179","categoryID":"11","label":"FW Amarr Empire Cruiser"},
{"value":"1180","categoryID":"11","label":"FW Caldari State Cruiser"},
{"value":"1181","categoryID":"11","label":"FW Gallente Federation Cruiser"},
{"value":"1182","categoryID":"11","label":"FW Minmatar Republic Cruiser"},
{"value":"1183","categoryID":"11","label":"FW Amarr Empire Battlecruiser"},
{"value":"1184","categoryID":"11","label":"FW Caldari State Battlecruiser"},
{"value":"1185","categoryID":"11","label":"FW Gallente Federation Battlecruiser"},
{"value":"1186","categoryID":"11","label":"FW Minmatar Republic Battlecruiser"},
{"value":"1189","categoryID":"7","label":"Micro Jump Drive"},
{"value":"1190","categoryID":"9","label":"Salvage Drone Blueprint"},
{"value":"1191","categoryID":"9","label":"Micro Jump Drive Blueprint"},
{"value":"1194","categoryID":"63","label":"Special Edition Commodities"},
{"value":"1195","categoryID":"63","label":"'Tournament Cards: New Eden Open YC 114'"},
{"value":"1197","categoryID":"9","label":"Special Edition Commodity Blueprints"},
{"value":"1198","categoryID":"2","label":"Orbital Target"},
{"value":"1199","categoryID":"7","label":"Fueled Armor Repairer"},
{"value":"1200","categoryID":"9","label":"Fueled Armor Repairer Blueprint"},
{"value":"1201","categoryID":"6","label":"Attack Battlecruiser"},
{"value":"1202","categoryID":"6","label":"Blockade Runner"},
{"value":"1206","categoryID":"17","label":"Security Tags"},
{"value":"1207","categoryID":"11","label":"Scatter Container"},
{"value":"1209","categoryID":"16","label":"Shields"},
{"value":"1210","categoryID":"16","label":"Armor"},
{"value":"1212","categoryID":"23","label":"Personal Hangar"},
{"value":"1213","categoryID":"16","label":"Targeting"},
{"value":"1216","categoryID":"16","label":"Engineering"},
{"value":"1217","categoryID":"16","label":"Scanning"},
{"value":"1218","categoryID":"16","label":"Resource Processing"},
{"value":"1220","categoryID":"16","label":"Neural Enhancement"},
{"value":"1222","categoryID":"9","label":"ECM Stabilizer Blueprint"},
{"value":"1223","categoryID":"7","label":"Scanning Upgrade"},
{"value":"1224","categoryID":"9","label":"Scanning Upgrade Blueprint"},
{"value":"1225","categoryID":"63","label":"'Tournament Cards: Alliance Tournament All Stars'"},
{"value":"1226","categoryID":"7","label":"Survey Probe Launcher"},
{"value":"1227","categoryID":"9","label":"Survey Probe Launcher Blueprint"},
{"value":"1228","categoryID":"20","label":"Cyber Targeting"},
{"value":"1229","categoryID":"20","label":"Cyber Resource Processing"},
{"value":"1230","categoryID":"20","label":"Cyber Scanning"},
{"value":"1231","categoryID":"20","label":"Cyber Biology"},
{"value":"1232","categoryID":"7","label":"Rig Resource Processing"},
{"value":"1233","categoryID":"7","label":"Rig Scanning"},
{"value":"1234","categoryID":"7","label":"Rig Targeting"},
{"value":"1238","categoryID":"7","label":"Scanning Upgrade Time"},
{"value":"1239","categoryID":"9","label":"Scanning Upgrade Time Blueprint"},
{"value":"1240","categoryID":"16","label":"Subsystems"},
{"value":"1241","categoryID":"16","label":"Planet Management"},
{"value":"1245","categoryID":"7","label":"Missile Launcher Rapid Heavy"},
{"value":"1246","categoryID":"22","label":"Mobile Depot"},
{"value":"1247","categoryID":"22","label":"Mobile Siphon Unit"},
{"value":"1248","categoryID":"17","label":"Empire Bounty Reimbursement Tags"},
{"value":"1249","categoryID":"22","label":"Mobile Cyno Inhibitor"},
{"value":"1250","categoryID":"22","label":"Mobile Tractor Unit"},
{"value":"1252","categoryID":"11","label":"Ghost Sites Angel Cartel Cruiser"},
{"value":"1255","categoryID":"11","label":"Ghost Sites Blood Raiders Cruiser"},
{"value":"1259","categoryID":"11","label":"Ghost Sites Guristas Cruiser"},
{"value":"1262","categoryID":"11","label":"Ghost Sites Serpentis Cruiser"},
{"value":"1265","categoryID":"11","label":"Ghost Sites Sanshas Cruiser"},
{"value":"1267","categoryID":"9","label":"Mobile Siphon Unit Blueprint"},
{"value":"1268","categoryID":"9","label":"Mobile Cynosural Inhibitor Blueprint"},
{"value":"1269","categoryID":"9","label":"Mobile Depot Blueprint"},
{"value":"1270","categoryID":"9","label":"Mobile Tractor Unit Blueprint"},
{"value":"1271","categoryID":"30","label":"Prosthetics"},
{"value":"1273","categoryID":"22","label":"Encounter Surveillance System"},
{"value":"1274","categoryID":"22","label":"Mobile Decoy Unit"},
{"value":"1275","categoryID":"22","label":"Mobile Scan Inhibitor"},
{"value":"1276","categoryID":"22","label":"Mobile Micro Jump Unit"},
{"value":"1277","categoryID":"9","label":"Encounter Surveillance System Blueprint"},
{"value":"1282","categoryID":"23","label":"Compression Array"},
{"value":"1283","categoryID":"6","label":"Expedition Frigate"},
{"value":"1285","categoryID":"11","label":"Asteroid Mordus Legion Commander Frigate"},
{"value":"1286","categoryID":"11","label":"Asteroid Mordus Legion Commander Cruiser"},
{"value":"1287","categoryID":"11","label":"Asteroid Mordus Legion Commander Battleship"},
{"value":"1288","categoryID":"11","label":"Ghost Sites Mordu's Legion"},
{"value":"1289","categoryID":"7","label":"Warp Accelerator"},
{"value":"1292","categoryID":"7","label":"Drone Tracking Enhancer"},
{"value":"1293","categoryID":"9","label":"Mobile Scan Inhibitor Blueprint"},
{"value":"1294","categoryID":"9","label":"Mobile Micro Jump Unit Blueprint"},
{"value":"1295","categoryID":"9","label":"Mobile Decoy Unit Blueprint"},
{"value":"1297","categoryID":"22","label":"Mobile Vault"},
{"value":"1299","categoryID":"7","label":"Jump Drive Economizer"},
{"value":"1301","categoryID":"5","label":"Services"},
{"value":"1304","categoryID":"35","label":"Generic Decryptor"},
{"value":"1305","categoryID":"6","label":"Tactical Destroyer"},
{"value":"1306","categoryID":"7","label":"Ship Modifiers"},
{"value":"1307","categoryID":"11","label":"Roaming Sleepers Cruiser"},
{"value":"1308","categoryID":"7","label":"Rig Anchor"},
{"value":"1309","categoryID":"9","label":"Tactical Destroyer Blueprint"},
{"value":"1310","categoryID":"11","label":"Drifter Battleship"},
{"value":"1311","categoryID":"5","label":"Super Kerr-Induced Nanocoatings"},
{"value":"1312","categoryID":"22","label":"Observatory Structures"},
{"value":"1313","categoryID":"7","label":"Entosis Link"},
{"value":"1314","categoryID":"17","label":"Unknown Components"},
{"value":"1316","categoryID":"2","label":"Entosis Command Node"},
{"value":"1317","categoryID":"9","label":"Infrastructure Upgrade Blueprint"},
{"value":"1318","categoryID":"9","label":"Entosis Link Blueprint"},
{"value":"1319","categoryID":"29","label":"Miscellaneous"},
{"value":"1320","categoryID":"65","label":"X-Large Citadel"},
{"value":"1321","categoryID":"66","label":"Structure Citadel Service Module"},
{"value":"1322","categoryID":"66","label":"Structure Drilling Service Module"},
{"value":"1323","categoryID":"66","label":"Structure Observatory Service Module"},
{"value":"1324","categoryID":"66","label":"Structure Stargate Service Module"},
{"value":"1325","categoryID":"66","label":"Structure Administration Service Module"},
{"value":"1326","categoryID":"66","label":"Structure Advertisement Service Module"},
{"value":"1327","categoryID":"66","label":"Structure Anti-Ship Launcher"},
{"value":"1328","categoryID":"66","label":"Structure AoE Missile Launcher"},
{"value":"1329","categoryID":"66","label":"Structure Energy Neutralizer"},
{"value":"1330","categoryID":"66","label":"Structure Defense Battery"},
{"value":"1331","categoryID":"66","label":"Structure Bumping Module"},
{"value":"1332","categoryID":"66","label":"Structure ECM"},
{"value":"1333","categoryID":"66","label":"Structure Doomsday Weapon"},
{"value":"1395","categoryID":"7","label":"Missile Guidance Enhancer"},
{"value":"1396","categoryID":"7","label":"Missile Guidance Computer"},
{"value":"1397","categoryID":"9","label":"Missile Guidance Enhancer Blueprint"},
{"value":"1399","categoryID":"9","label":"Missile Guidance Computer Blueprint"},
{"value":"1400","categoryID":"8","label":"Missile Guidance Script"},
{"value":"1402","categoryID":"11","label":"Amarr Navy Roaming Battleship"},
{"value":"1404","categoryID":"65","label":"Assembly Array"},
{"value":"1405","categoryID":"65","label":"Laboratory"},
{"value":"1406","categoryID":"65","label":"Drilling Platform"},
{"value":"1407","categoryID":"65","label":"Observatory Array"},
{"value":"1408","categoryID":"65","label":"Stargate"},
{"value":"1409","categoryID":"65","label":"Administration Hub"},
{"value":"1410","categoryID":"65","label":"Advertisement Center"},
{"value":"1411","categoryID":"11","label":"Amarr Navy Roaming Cruiser"},
{"value":"1412","categoryID":"11","label":"Amarr Navy Roaming Capital"},
{"value":"1413","categoryID":"11","label":"Amarr Navy Roaming Logistics"},
{"value":"1414","categoryID":"11","label":"Amarr Navy Roaming Frigate"},
{"value":"1415","categoryID":"66","label":"Structure Assembly Service Module"},
{"value":"1416","categoryID":"66","label":"Structure Research Service Module"},
{"value":"1418","categoryID":"66","label":"Structure Warfare Link"},
{"value":"1419","categoryID":"66","label":"Structure Remote Armor Repairer"},
{"value":"1420","categoryID":"66","label":"Structure Drone Augmentor Module"},
{"value":"1421","categoryID":"66","label":"Structure Remote Tracking Computer"},
{"value":"1424","categoryID":"66","label":"Structure Sensor Booster"},
{"value":"1425","categoryID":"66","label":"Structure Remote Sensor Booster"},
{"value":"1426","categoryID":"66","label":"Structure Missile Guidance Computer"},
{"value":"1427","categoryID":"66","label":"Structure Remote Missile Guidance Computer"},
{"value":"1428","categoryID":"66","label":"Structure Drone Navigation Computer"},
{"value":"1429","categoryID":"66","label":"Structure Ballistic Control System"},
{"value":"1430","categoryID":"66","label":"Structure CPU Enhancer"},
{"value":"1431","categoryID":"66","label":"Structure Remote Sensor Dampener"},
{"value":"1432","categoryID":"66","label":"Structure Tracking Disruptors"},
{"value":"1433","categoryID":"66","label":"Structure Target Painter"},
{"value":"1434","categoryID":"66","label":"Structure Tractor Beam"},
{"value":"1435","categoryID":"66","label":"Structure Reactor Control Unit"},
{"value":"1437","categoryID":"66","label":"Structure Remote Shield Booster"},
{"value":"1438","categoryID":"66","label":"Structure Remote Hull Repairer"},
{"value":"1439","categoryID":"66","label":"Structure Remote Capacitor Transmitter"},
{"value":"1440","categoryID":"66","label":"Structure Drone Damage Amplifier"},
{"value":"1441","categoryID":"66","label":"Structure Stasis Webifier"},
{"value":"1442","categoryID":"66","label":"Structure Warp Scrambler"},
{"value":"1443","categoryID":"66","label":"Structure Tracking Enhancer"},
{"value":"1444","categoryID":"66","label":"Structure Guidance Enhancer"},
{"value":"1445","categoryID":"66","label":"Structure Drone Tracking Enhancer"},
{"value":"1452","categoryID":"11","label":"Blood Raider Event Battleship"},
{"value":"1453","categoryID":"11","label":"Blood Raider Event Frigate"},
{"value":"1454","categoryID":"11","label":"Blood Raider Event Cruiser"},
{"value":"1455","categoryID":"11","label":"Blood Raider Event Battlecruiser"},
{"value":"1461","categoryID":"9","label":"Unknown Blueprint"},
{"value":"1462","categoryID":"9","label":"Structure Blueprints"},
{"value":"1463","categoryID":"9","label":"Structure Module Blueprints"},
{"value":"1465","categoryID":"11","label":"Mission Generic Supercarrier"},
{"value":"1467","categoryID":"9","label":"Structure - Administration Service Module Blueprint"},
{"value":"1468","categoryID":"9","label":"Structure - Advertisement Service Module Blueprint"},
{"value":"1469","categoryID":"9","label":"Structure - AoE Missile Launcher Blueprint"},
{"value":"1470","categoryID":"9","label":"Structure - Assembly Service Module Blueprint"},
{"value":"1471","categoryID":"9","label":"Structure - Ballistic Control System Blueprint"},
{"value":"1472","categoryID":"9","label":"Structure - Repulsor Field Blueprint"},
{"value":"1473","categoryID":"9","label":"Structure - Citadel Service Module Blueprint"},
{"value":"1474","categoryID":"9","label":"Structure - CPU Enhancer Blueprint"},
{"value":"1475","categoryID":"9","label":"Structure - Defense Battery Blueprint"},
{"value":"1476","categoryID":"9","label":"Structure - Doomsday Weapon Blueprint"},
{"value":"1477","categoryID":"9","label":"Structure - Drilling Service Module Blueprint"},
{"value":"1478","categoryID":"9","label":"Structure - Drone Augmentor Module Blueprint"},
{"value":"1479","categoryID":"9","label":"Structure - Drone Damage Amplifier Blueprint"},
{"value":"1480","categoryID":"9","label":"Structure - Drone Tracking Enhancer Blueprint"},
{"value":"1481","categoryID":"9","label":"Structure - ECM Blueprint"},
{"value":"1482","categoryID":"9","label":"Structure - Energy Neutralizer Blueprint"},
{"value":"1483","categoryID":"9","label":"Structure - Guidance Enhancer Blueprint"},
{"value":"1484","categoryID":"9","label":"Structure - Missile Guidance Computer Blueprint"},
{"value":"1485","categoryID":"9","label":"Structure - Missile Launcher Blueprint"},
{"value":"1486","categoryID":"9","label":"Structure - Observatory Service Module Blueprint"},
{"value":"1488","categoryID":"9","label":"Structure - Reactor Control Unit Blueprint"},
{"value":"1489","categoryID":"9","label":"Structure - Remote Armor Repairer Blueprint"},
{"value":"1490","categoryID":"9","label":"Structure - Remote Capacitor Transmitter Blueprint"},
{"value":"1491","categoryID":"9","label":"Structure - Remote Hull Repairer Blueprint"},
{"value":"1492","categoryID":"9","label":"Structure - Remote Missile Guidance Computer Blueprint"},
{"value":"1493","categoryID":"9","label":"Structure - Remote Sensor Booster Blueprint"},
{"value":"1494","categoryID":"9","label":"Structure - Remote Sensor Dampener Blueprint"},
{"value":"1495","categoryID":"9","label":"Structure - Remote Shield Booster Blueprint"},
{"value":"1496","categoryID":"9","label":"Structure - Remote Tracking Computer Blueprint"},
{"value":"1497","categoryID":"9","label":"Structure - Research Service Module Blueprint"},
{"value":"1498","categoryID":"9","label":"Structure - Sensor Booster Blueprint"},
{"value":"1499","categoryID":"9","label":"Structure - Stargate Service Module Blueprint"},
{"value":"1500","categoryID":"9","label":"Structure - Stasis Webifier Blueprint"},
{"value":"1501","categoryID":"9","label":"Structure - Target Painter Blueprint"},
{"value":"1503","categoryID":"9","label":"Structure - Tracking Disruptor Blueprint"},
{"value":"1504","categoryID":"9","label":"Structure - Tracking Enhancer Blueprint"},
{"value":"1505","categoryID":"9","label":"Structure - Ship Tractor Beam Blueprint"},
{"value":"1506","categoryID":"9","label":"Structure - Warfare Link Blueprint"},
{"value":"1507","categoryID":"9","label":"Structure - Warp Disruptor Blueprint"},
{"value":"1508","categoryID":"9","label":"Structure - Drone Navigation Computer Blueprint"},
{"value":"1517","categoryID":"9","label":"Structure - Assembly Rig Blueprint"},
{"value":"1520","categoryID":"9","label":"Structure - Laboratory Rig Blueprint"},
{"value":"1521","categoryID":"9","label":"Structure - Citadel Rig Blueprint"},
{"value":"1522","categoryID":"9","label":"Structure - Drilling Rig Blueprint"},
{"value":"1527","categoryID":"6","label":"Logistics Frigate"},
{"value":"1529","categoryID":"11","label":"Genericgroup1529"},
{"value":"1530","categoryID":"11","label":"Genericgroup1530"},
{"value":"1533","categoryID":"7","label":"Micro Jump Field Generators"},
{"value":"1534","categoryID":"6","label":"Command Destroyers"},
{"value":"1535","categoryID":"66","label":"Structure Signal Amplifier"},
{"value":"1536","categoryID":"9","label":"Structure - Signal Amplifier Blueprint"},
{"value":"1537","categoryID":"87","label":"Support Fighter"},
{"value":"1538","categoryID":"6","label":"Force Auxiliary"},
{"value":"1542","categoryID":"9","label":"Command Destroyer Blueprint"},
{"value":"1543","categoryID":"9","label":"Micro Jump Field Generator Blueprint"},
{"value":"1545","categoryID":"16","label":"Structure Management"},
{"value":"1546","categoryID":"8","label":"Structure Anti-Ship Missile"},
{"value":"1547","categoryID":"8","label":"Structure Flak Missile"},
{"value":"1548","categoryID":"8","label":"Structure AoE Missile"},
{"value":"1549","categoryID":"8","label":"Structure ECM script"},
{"value":"1550","categoryID":"8","label":"Structure Stasis Webifier Script"},
{"value":"1551","categoryID":"8","label":"Structure Warp Disruptor Script"},
{"value":"1559","categoryID":"8","label":"Structure Resistance Switcher Script"},
{"value":"1562","categoryID":"66","label":"Structure Flak Launcher"},
{"value":"1563","categoryID":"66","label":"Structure Resistance Switcher"},
{"value":"1564","categoryID":"9","label":"Structure - Resistance Switcher Blueprint"},
{"value":"1566","categoryID":"11","label":"Serpentis Event Frigate"},
{"value":"1567","categoryID":"11","label":"Serpentis Event Cruiser"},
{"value":"1568","categoryID":"11","label":"Serpentis Event Battlecruiser"},
{"value":"1569","categoryID":"8","label":"Guidance Disruption Script"},
{"value":"1570","categoryID":"66","label":"Structure Assembly Rig M - Small Tech I Ship"},
{"value":"1579","categoryID":"66","label":"Structure Assembly Rig M - Medium Tech I Ship"},
{"value":"1580","categoryID":"66","label":"Structure Assembly Rig M - Large Tech I Ship"},
{"value":"1581","categoryID":"66","label":"Structure Assembly Rig M - Small Tech II Ship"},
{"value":"1582","categoryID":"66","label":"Structure Assembly Rig M - Medium Tech II Ship"},
{"value":"1583","categoryID":"66","label":"Structure Assembly Rig M - Large Tech II Ship"},
{"value":"1584","categoryID":"66","label":"Structure Assembly Rig M - Drone"},
{"value":"1585","categoryID":"66","label":"Structure Assembly Rig M - Consumable"},
{"value":"1586","categoryID":"66","label":"Structure Assembly Rig M - Module"},
{"value":"1587","categoryID":"66","label":"Structure Assembly Rig L - Module, Consumable, Drone"},
{"value":"1588","categoryID":"66","label":"Structure Assembly Rig L - Tech I Ship"},
{"value":"1589","categoryID":"66","label":"Structure Assembly Rig L - Tech II Ship"},
{"value":"1590","categoryID":"66","label":"Structure Assembly Rig L - Tech II Component"},
{"value":"1591","categoryID":"66","label":"Structure Assembly Rig L - Tech I Capital Component"},
{"value":"1592","categoryID":"66","label":"Structure Assembly Rig L - Structure Component"},
{"value":"1593","categoryID":"66","label":"Structure Assembly Rig L - Subsystem"},
{"value":"1594","categoryID":"66","label":"Structure Assembly Rig XL - Equipment"},
{"value":"1595","categoryID":"66","label":"Structure Assembly Rig XL - Ship"},
{"value":"1596","categoryID":"66","label":"Structure Assembly Rig XL - All Components"},
{"value":"1598","categoryID":"66","label":"Structure Laboratory Rig M - Small Ship"},
{"value":"1599","categoryID":"66","label":"Structure Laboratory Rig M - Medium Ship"},
{"value":"1600","categoryID":"66","label":"Structure Laboratory Rig M - Large Ship"},
{"value":"1601","categoryID":"66","label":"Structure Laboratory Rig M - Drone"},
{"value":"1602","categoryID":"66","label":"Structure Laboratory Rig M - Consumable"},
{"value":"1603","categoryID":"66","label":"Structure Laboratory Rig M - Module"},
{"value":"1604","categoryID":"66","label":"Structure Laboratory Rig L - Module, Consumable, Drone"},
{"value":"1605","categoryID":"66","label":"Structure Laboratory Rig L - Ship"},
{"value":"1606","categoryID":"66","label":"Structure Laboratory Rig L - Component"},
{"value":"1607","categoryID":"66","label":"Structure Laboratory Rig L - Capital Component"},
{"value":"1608","categoryID":"66","label":"Structure Laboratory Rig L - Structure Component"},
{"value":"1609","categoryID":"66","label":"Structure Laboratory Rig L - Subsystem"},
{"value":"1610","categoryID":"66","label":"Structure Laboratory Rig XL - Equipment"},
{"value":"1611","categoryID":"66","label":"Structure Laboratory Rig XL - Ship"},
{"value":"1612","categoryID":"66","label":"Structure Laboratory Rig XL - All Components"},
{"value":"1613","categoryID":"66","label":"Structure Citadel Rig M - Missile Application"},
{"value":"1614","categoryID":"66","label":"Structure Citadel Rig M - Missile Projection"},
{"value":"1615","categoryID":"66","label":"Structure Citadel Rig M - Energy Neutralizer Projection"},
{"value":"1616","categoryID":"66","label":"Structure Citadel Rig M - Energy Neutralizer Cap Reduction"},
{"value":"1617","categoryID":"66","label":"Structure Citadel Rig M - Drone Hitpoints"},
{"value":"1618","categoryID":"66","label":"Structure Citadel Rig M - Drone Speed"},
{"value":"1619","categoryID":"66","label":"Structure Citadel Rig M - EW projection"},
{"value":"1620","categoryID":"66","label":"Structure Citadel Rig M - EW Cap Reduction"},
{"value":"1621","categoryID":"66","label":"Structure Citadel Rig M - Max Targets"},
{"value":"1622","categoryID":"66","label":"Structure Citadel Rig M - Sensor Resolution"},
{"value":"1623","categoryID":"66","label":"Structure Citadel Rig M - Office Number"},
{"value":"1624","categoryID":"66","label":"Structure Citadel Rig M - Jump Clone Number"},
{"value":"1625","categoryID":"66","label":"Structure Citadel Rig M - Jump Clone Tax"},
{"value":"1626","categoryID":"66","label":"Structure Citadel Rig M - PI production"},
{"value":"1627","categoryID":"66","label":"Structure Citadel Rig M - Customs Office Tax"},
{"value":"1628","categoryID":"66","label":"Structure Citadel Rig M - LP Store Price"},
{"value":"1629","categoryID":"66","label":"Structure Citadel Rig L - Missile Application and Projection"},
{"value":"1631","categoryID":"66","label":"Structure Citadel Rig L - Drone Hitpoints and Speed"},
{"value":"1632","categoryID":"66","label":"Structure Citadel Rig L - EW Projection and Cap Reduction"},
{"value":"1633","categoryID":"66","label":"Structure Citadel Rig L - AoE Launcher Application and Projection"},
{"value":"1634","categoryID":"66","label":"Structure Citadel Rig L - Point Defense Battery Application and Projection"},
{"value":"1635","categoryID":"66","label":"Structure Citadel Rig L - Max Targets and Sensor Resolution"},
{"value":"1636","categoryID":"66","label":"Structure Citadel Rig L - Office, Jump Clone and Tax"},
{"value":"1637","categoryID":"66","label":"Structure Citadel Rig L - PI, Customs Office Tax"},
{"value":"1638","categoryID":"66","label":"Structure Citadel Rig L - Market and LP Store"},
{"value":"1639","categoryID":"66","label":"Structure Citadel Rig XL - Missile and AoE Missile"},
{"value":"1640","categoryID":"66","label":"Structure Citadel Rig XL - Drone and PDB"},
{"value":"1641","categoryID":"66","label":"Structure Citadel Rig XL - Energy Neutralizer and EW"},
{"value":"1642","categoryID":"66","label":"Structure Citadel Rig XL - Doomsday and Targeting"},
{"value":"1644","categoryID":"66","label":"Structure Citadel Rig XL - Office, Jump Clone, PI, Customs Office, Market"},
{"value":"1647","categoryID":"66","label":"Structure Drilling Rig M - Reprocessing"},
{"value":"1648","categoryID":"66","label":"Structure Drilling Rig L - Reprocessing"},
{"value":"1649","categoryID":"66","label":"Structure Drilling Rig XL - Reprocessing"},
{"value":"1652","categoryID":"87","label":"Light Fighter"},
{"value":"1653","categoryID":"87","label":"Heavy Fighter"},
{"value":"1656","categoryID":"65","label":"XXLarge Citadel"},
{"value":"1657","categoryID":"65","label":"Medium Citadel"},
{"value":"1658","categoryID":"65","label":"Large Citadel"},
{"value":"1664","categoryID":"11","label":"Guristas Event Frigate"},
{"value":"1665","categoryID":"11","label":"Guristas Event Cruiser"},
{"value":"1666","categoryID":"11","label":"Guristas Event Battlecruiser"},
{"value":"1667","categoryID":"11","label":"Guristas Event Battleship"},
{"value":"1670","categoryID":"30","label":"Augmentations"},
{"value":"1672","categoryID":"7","label":"Stasis Grappler"},
{"value":"350858","categoryID":"350001","label":"Infantry Weapons"},
{"value":"351064","categoryID":"350001","label":"Infantry Dropsuits"},
{"value":"351121","categoryID":"350001","label":"Infantry Modules"},
{"value":"351210","categoryID":"350001","label":"Infantry Vehicles"},
{"value":"351648","categoryID":"350001","label":"Infantry Skills"},
{"value":"351844","categoryID":"350001","label":"Infantry Equipment"},
{"value":"354641","categoryID":"350001","label":"Infantry Skill Enhancers"},
{"value":"354753","categoryID":"350001","label":"Infantry Installations"},
{"value":"364204","categoryID":"350001","label":"Surface Infrastructure"},
{"value":"367487","categoryID":"350001","label":"'Services '"},
{"value":"367580","categoryID":"350001","label":"Agents"},
{"value":"367594","categoryID":"350001","label":"Visual Customization"},
{"value":"367774","categoryID":"350001","label":"Salvage Containers"},
{"value":"367776","categoryID":"350001","label":"Salvage Decryptors"},
{"value":"368656","categoryID":"350001","label":"Battle Salvage"},
{"value":"368666","categoryID":"350001","label":"Warbarge"},
{"value":"368726","categoryID":"350001","label":"Infantry Color Skin"}
]